{
    "USE_GPU": true,
    "LOAD_CACHE": false,
    "SAVE_CACHE": false,
    "DOWNSCALE_METHOD": "scipy",
    "OPENCV_INTERPOLATION": "area",
    "DOWNSCALE_FACTORS": [
        1,
        1,
        1
    ],
    "MAX_THRESHOLD_PERCENTILE": 99.7,
    "VESSELNESS_AORTA": {
        "sigmas": [
            2.5
        ],
        "black_ridges": false,
        "alpha": 0.5,
        "beta": 1.0,
        "gamma": 30,
        "normalization": "none"
    },
    "VESSELNESS_ARTERY": {
        "sigmas": [
            1.5,
            2.0,
            2.5,
            3.0
        ],
        "black_ridges": false,
        "alpha": 0.5,
        "beta": 0.5,
        "gamma": 55,
        "normalization": "none"
    },
    "CIRCLE_DETECTION": {
        "radii_start_px": 38,
        "radii_end_px": 62,
        "radius_step_px": 1,
        "tol_radius_mm": 9.0,
        "tol_distance_mm": 20.0,
        "quadrant_offset": [
            30,
            30
        ],
        "max_slice_miss_threshold": 5,
        "neighbor_distance_threshold": 5,
        "total_num_peaks_initial": 15,
        "total_num_peaks": 15,
        "canny_sigma": 3,
        "use_local_roi": true,
        "local_roi_padding": 30
    },
    "LEVEL_SET": {
        "radius_reduction_factor": 0.15,
        "num_iter": 70,
        "balloon": 0.8,
        "smoothing": 2,
        "leak_removal_radius": 2
    },
    "OSTIA_DETECTION": {
        "top_n": 2000,
        "max_z_diff_mm": 40.0,
        "lower_fraction": 0.8,
        "min_center_distance_factor": 0.85,
        "min_lateral_factor": 0.4,
        "erosion_radius": 4
    },
    "OSTIA_VALIDATION": {
        "distance_threshold_mm": 8.0
    },
    "REGION_GROWING": {
        "max_volume": 100000,
        "switch_at_voxels": 2000,
        "min_vesselness_fraction": 0.078,
        "threshold_divisor": 5,
        "relaxed_floor_factor": 0.97,
        "comparison_window": 1,
        "smooth_relaxation": true,
        "verbose": false
    },
    "POSTPROCESSING": {
        "closing_radius": 3,
        "dilation_radius": 2
    }
}